[
    {
        "question": "All predisposes to isoimmunisation in a Rh-ve female except.",
        "exp": "Ans. is 'a' i. e. Advanced maternal age Following are the conditions predisposing to isoimmunization in Rh-ve femaleabortionchorionic villous samplingamniocentesisantepartum Haemorrhage attempted versioncaesarian section*manual removal of placenta Recent studies state that there is continuous feto-maternal bleed occurring throughout normal pregnancies. So it is not advisable to go beyond the expected date of pregnancy. Hence postdated pregnancy is another risk-factor for isoimmunization. *",
        "cop": 1,
        "opa": "Advaned maternal age",
        "opb": "Antepartum haemorrhage",
        "opc": "Caesarian section",
        "opd": "Postdated pregnancy",
        "subject_name": "Gynaecology & Obstetrics",
        "topic_name": "Hematological Disorders",
        "id": "5cb23af8-1ba1-40e6-a8d0-1418ad7f7c65",
        "choice_type": "multi"
    }
]