[
    {
        "question": "Most common complication of ileostomy is:",
        "exp": "- Overall M/c complication of ileostomy -Skin excoriation / dermatitis - MC early complication of ileostomy - Ischemia / necrosis - MC complication of both end colostomy and loop colostomy - Parastomal hernia - Parastomal hernia is more common in END colostomy (due to extensive dissection) - Prolapse is more common in LOOP colostomy (due to larger opening)",
        "cop": 2,
        "opa": "Ischemic necrosis",
        "opb": "Skin irritation",
        "opc": "Prolapse",
        "opd": "Parastomal hernia",
        "subject_name": "Surgery",
        "topic_name": "Ileostomy and colostomy",
        "id": "7dea2360-670f-4da8-a522-c5d0df5a2c12",
        "choice_type": "single"
    },
    {
        "question": "Parastomal hernia is most frequently seen with:",
        "exp": "Parastomal hernia is most frequently seen with end colostomy. STOMAL COMPLICATIONS MC complication of both end & loop colostomy: Parastomal herniaQ Parastomal hernia is more common in end colostomyQas compared to loop colostomy. Prolapse is more common in loop colostomyQ MC complication of ileostomy: Skin irritationQ MC early complication of ileostomy: Ischemic necrosisQ",
        "cop": 1,
        "opa": "End colostomy",
        "opb": "Loop colostomy",
        "opc": "End ileostomy",
        "opd": "Loop ileostomy",
        "subject_name": "Surgery",
        "topic_name": "Ileostomy and colostomy",
        "id": "5cc27bbf-e2f3-4725-a1c4-4db91b7402ae",
        "choice_type": "single"
    }
]